Metadata-Version: 2.1
Name: odoo14-addon-edi_sale_input_oca
Version: 14.0.1.2.0
Summary: Process incoming sale orders with the EDI framework.
Home-page: https://github.com/OCA/edi
Author: Camptocamp,Odoo Community Association (OCA)
Author-email: support@odoo-community.org
License: AGPL-3
Classifier: Programming Language :: Python
Classifier: Framework :: Odoo
Classifier: Framework :: Odoo :: 14.0
Classifier: License :: OSI Approved :: GNU Affero General Public License v3
Classifier: Development Status :: 3 - Alpha
Requires-Python: >=3.6
Requires-Dist: odoo14-addon-edi-record-metadata-oca
Requires-Dist: odoo14-addon-edi-sale-oca
Requires-Dist: odoo14-addon-sale-order-import
Requires-Dist: odoo<14.1dev,>=14.0a
